{"version":2,"droids":[{"template":"Cyb-ComEng","id":676,"position":[12608,12992],"rotation":0,"startpos":0},{"template":"ConstructionDroid","id":710,"position":[14272,13760],"rotation":0,"startpos":2},{"template":"Cyb-ComEng","id":677,"position":[12992,12992],"rotation":0,"startpos":1},{"template":"ConstructionDroid","id":703,"position":[11712,11712],"rotation":0,"startpos":2},{"template":"ConstructionDroid","id":704,"position":[11584,11840],"rotation":0,"startpos":2},{"template":"ConstructionDroid","id":705,"position":[11840,11840],"rotation":0,"startpos":2},{"template":"ConstructionDroid","id":706,"position":[11712,11968],"rotation":0,"startpos":2},{"template":"ConstructionDroid","id":707,"position":[11712,11840],"rotation":0,"startpos":2},{"template":"ConstructionDroid","id":708,"position":[14144,13888],"rotation":0,"startpos":2},{"template":"ConstructionDroid","id":709,"position":[14272,13888],"rotation":0,"startpos":2},{"template":"ConstructionDroid","id":712,"position":[14272,14016],"rotation":0,"startpos":2},{"template":"Transporter","id":675,"position":[12864,12864],"rotation":0,"startpos":1},{"template":"Transporter","id":674,"position":[12736,12864],"rotation":0,"startpos":0},{"template":"ConstructionDroid","id":711,"position":[14400,13888],"rotation":0,"startpos":2},{"template":"ConstructionDroid","id":723,"position":[24512,24640],"rotation":0,"startpos":6},{"template":"ConstructionDroid","id":725,"position":[24640,24512],"rotation":0,"startpos":4},{"template":"ConstructionDroid","id":726,"position":[24512,24512],"rotation":0,"startpos":3},{"template":"ConstructionDroid","id":724,"position":[24640,24640],"rotation":0,"startpos":5}]}