{"version":2,"structures":[{"name":"A0CommandCentre","id":1,"position":[8448,8192],"rotation":0,"startpos":1},{"name":"A0CommandCentre","id":2,"position":[7936,8192],"rotation":0,"startpos":0},{"name":"A0CommandCentre","id":3,"position":[768,15616],"rotation":0,"startpos":5},{"name":"A0Sat-linkCentre","id":4,"position":[512,15872],"rotation":0,"startpos":5},{"name":"A0CommandCentre","id":5,"position":[768,768],"rotation":0,"startpos":4},{"name":"A0Sat-linkCentre","id":6,"position":[512,512],"rotation":0,"startpos":4},{"name":"A0CommandCentre","id":7,"position":[15616,768],"rotation":0,"startpos":3},{"name":"A0Sat-linkCentre","id":8,"position":[15872,512],"rotation":0,"startpos":3},{"name":"A0CommandCentre","id":9,"position":[15616,15616],"rotation":0,"startpos":2},{"name":"A0Sat-linkCentre","id":10,"position":[15872,15872],"rotation":0,"startpos":2}]}