{"version":2,"droids":[{"template":"ConstructionDroid","id":267,"position":[2112,17216],"rotation":32768,"startpos":4},{"template":"ConstructionDroid","id":268,"position":[2112,17344],"rotation":32768,"startpos":5},{"template":"ConstructionDroid","id":32,"position":[1728,1984],"rotation":0,"startpos":0},{"template":"ConstructionDroid","id":33,"position":[1856,1984],"rotation":0,"startpos":0},{"template":"ConstructionDroid","id":34,"position":[1728,2112],"rotation":0,"startpos":0},{"template":"ConstructionDroid","id":55,"position":[6464,14400],"rotation":0,"startpos":1},{"template":"ConstructionDroid","id":57,"position":[6464,14272],"rotation":0,"startpos":1},{"template":"ConstructionDroid","id":35,"position":[1856,2112],"rotation":0,"startpos":0},{"template":"ConstructionDroid","id":56,"position":[6336,14400],"rotation":0,"startpos":1},{"template":"ConstructionDroid","id":58,"position":[6336,14272],"rotation":0,"startpos":1},{"template":"ConstructionDroid","id":266,"position":[2112,17088],"rotation":32768,"startpos":3},{"template":"ConstructionDroid","id":265,"position":[2112,16960],"rotation":32768,"startpos":2}]}